coesi-0.1.0.dist-info/licenses/LICENSE
src/__init__.py
src/cli.py
src/utils.py
coesi-0.1.0.dist-info/METADATA
coesi-0.1.0.dist-info/WHEEL
coesi-0.1.0.dist-info/entry_points.txt
coesi-0.1.0.dist-info/top_level.txt
coesi-0.1.0.dist-info/RECORD
