Metadata-Version: 2.4
Name: coesi
Version: 0.1.0
Summary: COESI Platform CLI - Command line interface for managing COESI Docker deployments
Author-email: Reza Taheri <taheri.reza94@gmail.com>
License: MIT
Project-URL: Homepage, https://github.com/rezathriii/coesi-cli
Project-URL: Documentation, https://github.com/rezathriii/coesi-cli#readme
Project-URL: Repository, https://github.com/rezathriii/coesi-cli.git
Project-URL: Bug Reports, https://github.com/rezathriii/coesi-cli/issues
Keywords: coesi,docker,deployment,cli,devops
Classifier: Development Status :: 4 - Beta
Classifier: Intended Audience :: Developers
Classifier: License :: OSI Approved :: MIT License
Classifier: Operating System :: OS Independent
Classifier: Programming Language :: Python :: 3
Classifier: Programming Language :: Python :: 3.8
Classifier: Programming Language :: Python :: 3.9
Classifier: Programming Language :: Python :: 3.10
Classifier: Programming Language :: Python :: 3.11
Classifier: Programming Language :: Python :: 3.12
Classifier: Topic :: Software Development :: Libraries :: Python Modules
Classifier: Topic :: System :: Systems Administration
Requires-Python: >=3.8
License-File: LICENSE
Requires-Dist: click>=8.0.0
Requires-Dist: docker>=6.0.0
Requires-Dist: pyyaml>=6.0
Requires-Dist: rich>=13.0.0
Requires-Dist: python-dotenv>=1.0.0
Provides-Extra: dev
Requires-Dist: pytest>=7.0; extra == "dev"
Requires-Dist: pytest-cov>=4.0; extra == "dev"
Requires-Dist: black>=23.0; extra == "dev"
Requires-Dist: flake8>=6.0; extra == "dev"
Requires-Dist: mypy>=1.0; extra == "dev"
Requires-Dist: twine>=4.0; extra == "dev"
Requires-Dist: build>=0.10; extra == "dev"
Requires-Dist: types-docker>=6.0; extra == "dev"
Dynamic: license-file
